villagewars/__init__.py
villagewars/cheats.txt
villagewars/assets/Achievement.png
villagewars/assets/BG_Sand.png
villagewars/assets/BG_SciFi.png
villagewars/assets/BtnPlay.png
villagewars/assets/BtnPlay_hov.png
villagewars/assets/BtnReset.png
villagewars/assets/BtnSignin.png
villagewars/assets/BtnSignup.png
villagewars/assets/Button.png
villagewars/assets/Crate.png
villagewars/assets/CrateRubble.png
villagewars/assets/Crate_hurt.png
villagewars/assets/CreatingAcount.png
villagewars/assets/Disconnected.png
villagewars/assets/Done.png
villagewars/assets/Drop.png
villagewars/assets/DropSmall.png
villagewars/assets/Edit.png
villagewars/assets/Enemy_01.png
villagewars/assets/Enemy_02.png
villagewars/assets/Enemy_03.png
villagewars/assets/Enemy_04.png
villagewars/assets/Enemy_05.png
villagewars/assets/Enemy_05_hurt.png
villagewars/assets/LargeExplosion1.png
villagewars/assets/LargeExplosion2.png
villagewars/assets/LargeExplosion3.png
villagewars/assets/Setting.png
villagewars/assets/Setting_walls.png
villagewars/assets/SigningIn.png
villagewars/assets/SmallExplosion1.png
villagewars/assets/SmallExplosion2.png
villagewars/assets/SmallExplosion3.png
villagewars/assets/SplashLarge1.png
villagewars/assets/SplashLarge2.png
villagewars/assets/SplashLarge3.png
villagewars/assets/Startgame_btn.png
villagewars/assets/Startgame_btn_locked.png
villagewars/assets/Startgame_btn_over.png
villagewars/assets/TNT.png
villagewars/assets/addserver.png
villagewars/assets/addserver_hov.png
villagewars/assets/balloon.png
villagewars/assets/balloon2.png
villagewars/assets/cancel.png
villagewars/assets/castle_wall.png
villagewars/assets/castle_wall_up.png
villagewars/assets/diffserver.png
villagewars/assets/diffserver_hov.png
villagewars/assets/explode1.png
villagewars/assets/explode2.png
villagewars/assets/explode3.png
villagewars/assets/food.png
villagewars/assets/food_mine.png
villagewars/assets/food_used.png
villagewars/assets/gate.png
villagewars/assets/gold.png
villagewars-1.5.2.dist-info/METADATA
villagewars-1.5.2.dist-info/WHEEL
villagewars-1.5.2.dist-info/licenses/LICENSE
villagewars-1.5.2.dist-info/RECORD
